streamlit_bokeh3_events/__init__.py
streamlit_bokeh3_events/frontend/build/asset-manifest.json
streamlit_bokeh3_events/frontend/build/bootstrap.min.css
streamlit_bokeh3_events/frontend/build/index.html
streamlit_bokeh3_events/frontend/build/static/js/main.a9d1ae85.js
streamlit_bokeh3_events-0.1.4.dist-info/LICENSE
streamlit_bokeh3_events-0.1.4.dist-info/METADATA
streamlit_bokeh3_events-0.1.4.dist-info/WHEEL
streamlit_bokeh3_events-0.1.4.dist-info/top_level.txt
streamlit_bokeh3_events-0.1.4.dist-info/RECORD
